uniql/EvaluatorAndParserTest.py
uniql/__init__.py
uniql/bytecode.py
uniql/bytecode_compiler.py
uniql/cli.py
uniql/evaluator.py
uniql/parser.py
uniql/tokenizer.py
uniql/vm.py
uniql/backup/cli/cli0105.py
uniql/backup/evaluator/evaluator0103.py
uniql/backup/parser/parser0103.py
uniql/commands/__init__.py
uniql/commands/eval_cmd.py
uniql/commands/mongodb_cmd.py
uniql/commands/tinydb_cmd.py
uniql/engines/__init__.py
uniql/engines/mongodb/MongoTransformer.py
uniql/engines/mongodb/__init__.py
uniql/engines/mongodb/insertDataToMongodb.py
uniql/engines/mongodb/mongodb_tran_example.py
uniql/engines/mongodb/backup/MongoTransformer/MongoTransformer0104.py
uniql/engines/mongodb/backup/MongoTransformer/MongoTransformer0106.py
uniql/engines/mongodb/backup/MongoTransformer/MongoTransformer0109.py
uniql/engines/sql/__init__.py
uniql/engines/tinydb/TinyDBTransformer.py
uniql/engines/tinydb/__init__.py
uniql-0.1.5.dist-info/METADATA
uniql-0.1.5.dist-info/WHEEL
uniql-0.1.5.dist-info/entry_points.txt
uniql-0.1.5.dist-info/top_level.txt
uniql-0.1.5.dist-info/RECORD
