Metadata-Version: 2.4
Name: uniql
Version: 0.1.5
Summary: Unified Query Language - A unified query language for diffirent multiple query language
Requires-Dist: typer
